ssb_pubmd/__main__.py
ssb_pubmd/adapters/cli.py
ssb_pubmd/adapters/cms_client.py
ssb_pubmd/adapters/local_storage.py
ssb_pubmd/adapters/secret_manager_client.py
ssb_pubmd/config.py
ssb_pubmd/enonic_cms_manager.py
ssb_pubmd/models.py
ssb_pubmd/ports.py
ssb_pubmd/py.typed
ssb_pubmd-0.1.0.dist-info/LICENSE
ssb_pubmd-0.1.0.dist-info/METADATA
ssb_pubmd-0.1.0.dist-info/WHEEL
ssb_pubmd-0.1.0.dist-info/entry_points.txt
ssb_pubmd-0.1.0.dist-info/RECORD
