Metadata-Version: 2.3
Name: ssb-pubmd
Version: 0.1.0
Summary: SSB Pubmd
License: MIT
Author: Olav Landsverk
Author-email: stud-oll@ssb.no
Requires-Python: >=3.10,<4.0
Classifier: Development Status :: 3 - Alpha
Classifier: License :: OSI Approved :: MIT License
Classifier: Programming Language :: Python :: 3
Classifier: Programming Language :: Python :: 3.10
Classifier: Programming Language :: Python :: 3.11
Classifier: Programming Language :: Python :: 3.12
Classifier: Programming Language :: Python :: 3.13
Requires-Dist: cryptography (>=45.0.5,<46.0.0)
Requires-Dist: google-cloud-secret-manager (>=2.24.0,<3.0.0)
Requires-Dist: nbformat (>=5.10.4,<6.0.0)
Requires-Dist: pyjwt (>=2.10.1,<3.0.0)
Requires-Dist: requests (>=2.32.4,<3.0.0)
Requires-Dist: types-requests (>=2.32.4.20250611,<3.0.0.0)
Project-URL: Changelog, https://github.com/statisticsnorway/ssb-pubmd/releases
Project-URL: Documentation, https://statisticsnorway.github.io/ssb-pubmd
Project-URL: Homepage, https://github.com/statisticsnorway/ssb-pubmd
Project-URL: Repository, https://github.com/statisticsnorway/ssb-pubmd
